rhubarb/__init__.py
rhubarb/_core.py
rhubarb/backends/base.py
rhubarb/backends/exceptions.py
rhubarb/backends/kafka.py
rhubarb/backends/memory.py
rhubarb/backends/postgres.py
rhubarb/backends/rabbitmq.py
rhubarb/backends/redis.py
rhubarb/event.py
rhubarb/py.typed
rhubarb_py-1.8.6.dist-info/LICENSE
rhubarb_py-1.8.6.dist-info/METADATA
rhubarb_py-1.8.6.dist-info/WHEEL
rhubarb_py-1.8.6.dist-info/RECORD
