Metadata-Version: 2.1
Name: rhubarb-py
Version: 1.8.6
Summary: Rhubarb is a library that simplifies realtime streaming for a number of backends into a single API
Home-page: https://github.com/mopeyjellyfish/rhubarb
License: MIT
Author: mopeyjellyfish
Author-email: dev@davidhall.tech
Requires-Python: >=3.9,<4.0
Classifier: Development Status :: 3 - Alpha
Classifier: Intended Audience :: Developers
Classifier: License :: OSI Approved :: MIT License
Classifier: Operating System :: OS Independent
Classifier: Programming Language :: Python :: 3
Classifier: Programming Language :: Python :: 3.9
Classifier: Programming Language :: Python :: 3.10
Classifier: Programming Language :: Python :: 3.11
Classifier: Topic :: Software Development :: Libraries :: Python Modules
Provides-Extra: kafka
Provides-Extra: postgres
Provides-Extra: rabbitmq
Provides-Extra: redis
Requires-Dist: aio-pika (>=6.8,<10.0) ; extra == "rabbitmq"
Requires-Dist: aiokafka (>=0.7.2,<0.9.0) ; extra == "kafka"
Requires-Dist: anyio (>=3.4.0,<4.0.0)
Requires-Dist: asyncpg (>=0.24,<0.28) ; extra == "postgres"
Requires-Dist: redis (>=4.3.4,<5.0.0) ; extra == "redis"
Project-URL: Repository, https://github.com/mopeyjellyfish/rhubarb
